osxrelocator/__init__.py
osxrelocator-1.0.1.dist-info/DESCRIPTION.rst
osxrelocator-1.0.1.dist-info/entry_points.txt
osxrelocator-1.0.1.dist-info/METADATA
osxrelocator-1.0.1.dist-info/metadata.json
osxrelocator-1.0.1.dist-info/RECORD
osxrelocator-1.0.1.dist-info/top_level.txt
osxrelocator-1.0.1.dist-info/WHEEL
