Metadata-Version: 2.0
Name: osxrelocator
Version: 1.0.1
Summary: Utility to relocate OSX libraries
Home-page: https://github.com/tito/osxrelocator
Author: Mathieu Virbel
Author-email: mat@meltingrocks.com
License: LGPL2
Keywords: osx libraries relocation setuptools development
Platform: UNKNOWN
Classifier: Development Status :: 5 - Production/Stable
Classifier: Intended Audience :: Developers
Classifier: Topic :: Software Development :: Build Tools
Classifier: License :: OSI Approved :: GNU Lesser General Public License v2 (LGPLv2)
Classifier: Programming Language :: Python :: 2
Classifier: Programming Language :: Python :: 3
